datasets/__init__.py
datasets/cli.py
datasets/fast_seq_parser.py
datasets/open_dataset_client.py
datasets/parser.py
datasets/pt_dataset.py
datasets/seq_parser.py
datasets/textline_parser.py
datasets/tf_dataset.py
datasets/agumentation/__init__.py
datasets/cleaner/__init__.py
datasets/utils/__init__.py
datasets/utils/common_struct.py
datasets/utils/data_processor.py
datasets/utils/token_dicts.py
datasets/utils/tokenizer.py
ml_dataset-0.0.17.dist-info/AUTHORS.rst
ml_dataset-0.0.17.dist-info/LICENSE
ml_dataset-0.0.17.dist-info/METADATA
ml_dataset-0.0.17.dist-info/WHEEL
ml_dataset-0.0.17.dist-info/entry_points.txt
ml_dataset-0.0.17.dist-info/top_level.txt
ml_dataset-0.0.17.dist-info/RECORD
