Metadata-Version: 2.1
Name: ml-dataset
Version: 0.0.17
Summary: datasets for easy machine learning use
Home-page: https://github.com/yinochaos/datasets
Author: yinochaos
Author-email: pspcxl@163.com
License: Apache Software License 2.0
Keywords: ml-dataset
Platform: UNKNOWN
Classifier: Development Status :: 2 - Pre-Alpha
Classifier: Intended Audience :: Developers
Classifier: License :: OSI Approved :: Apache Software License
Classifier: Natural Language :: English
Classifier: Programming Language :: Python :: 3
Classifier: Programming Language :: Python :: 3.5
Classifier: Programming Language :: Python :: 3.6
Classifier: Programming Language :: Python :: 3.7
Classifier: Programming Language :: Python :: 3.8
Requires-Python: >=3.5
Requires-Dist: scipy
Requires-Dist: tdqm
Requires-Dist: python-speech-features
Requires-Dist: numpy
Requires-Dist: soundfile
